setup.py
dblog/__init__.py
dblog/logflask.py
dblog/logger.py
dblog/orm.py
dblog.egg-info/PKG-INFO
dblog.egg-info/SOURCES.txt
dblog.egg-info/dependency_links.txt
dblog.egg-info/requires.txt
dblog.egg-info/top_level.txt