Metadata-Version: 1.0
Name: dblog
Version: 0.3.2
Summary: A Python logging library that supports databases
Home-page: https://github.com/alex-sherman/python-dblog
Author: Alex Sherman
Author-email: asherman1024@gmail.com
License: UNKNOWN
Platform: UNKNOWN
